farcaster/__init__.py
farcaster/client.py
farcaster/config.py
farcaster/models.py
farcaster/py.typed
farcaster/utils/__init__.py
farcaster/utils/stream_generator.py
farcaster-0.7.10.dist-info/LICENSE
farcaster-0.7.10.dist-info/METADATA
farcaster-0.7.10.dist-info/WHEEL
farcaster-0.7.10.dist-info/RECORD
