Metadata-Version: 2.1
Name: farcaster
Version: 0.7.10
Summary: farcaster-py is a Python SDK for the Farcaster Protocol
Home-page: https://github.com/a16z/farcaster-py
License: MIT
Author: Andreessen Horowitz
Author-email: crypto-engineering@a16z.com
Requires-Python: >=3.8.0,<4.0.0
Classifier: Development Status :: 3 - Alpha
Classifier: Intended Audience :: Developers
Classifier: License :: OSI Approved :: MIT License
Classifier: Operating System :: OS Independent
Classifier: Programming Language :: Python :: 3
Classifier: Programming Language :: Python :: 3.8
Classifier: Programming Language :: Python :: 3.9
Classifier: Programming Language :: Python :: 3.10
Classifier: Programming Language :: Python :: 3.11
Classifier: Topic :: Software Development :: Libraries :: Python Modules
Requires-Dist: canonicaljson (>=1.6.4,<3.0.0)
Requires-Dist: eth-account (>=0.8.0,<0.9.0)
Requires-Dist: importlib_metadata (>=4.5.0,<5.0.0) ; python_version < "3.8"
Requires-Dist: parsimonious (>=0.8.1,<0.10.0)
Requires-Dist: pydantic (>=1.9.2,<3.0.0)
Requires-Dist: pyhumps (>=3.7.2,<4.0.0)
Requires-Dist: python-dotenv (>=0.21,<1.1)
Requires-Dist: requests (>=2.28.1,<3.0.0)
Project-URL: Repository, https://github.com/a16z/farcaster-py
